P2P/__init__.py
P2P/app.py
P2P/blockchain.py
P2P/connection.py
P2P/file.py
P2P/message.py
P2P/node.py
P2P/vars.py
netzwerk-0.0.1.dist-info/LICENSE
netzwerk-0.0.1.dist-info/METADATA
netzwerk-0.0.1.dist-info/WHEEL
netzwerk-0.0.1.dist-info/top_level.txt
netzwerk-0.0.1.dist-info/RECORD
