Metadata-Version: 2.1
Name: netzwerk
Version: 0.0.1
Summary: Peer to peer decentralised networking package
Home-page: https://github.com/NoelKaczmarek/P2P
Author: Noel Kaczmarek
Author-email: noel.kaczmarek@gmail.com
License: UNKNOWN
Platform: UNKNOWN
Classifier: Programming Language :: Python :: 3
Classifier: License :: OSI Approved :: MIT License
Classifier: Operating System :: OS Independent
Requires-Python: >=3.6
